a2grunner/__init__.py
a2grunner/localrunner.py
a2grunner/stdouts_redirects.py
a2grunner-0.0.5.dist-info/METADATA
a2grunner-0.0.5.dist-info/WHEEL
a2grunner-0.0.5.dist-info/top_level.txt
a2grunner-0.0.5.dist-info/RECORD
