Metadata-Version: 2.1
Name: a2grunner
Version: 0.0.5
Summary: A2G Runner for Local Workflow
Author: Carlos Alvarado
Author-email: <carlos@alert2gain.com>
Keywords: python,a2g base-a2grunner
Classifier: Development Status :: 3 - Alpha
Classifier: Intended Audience :: Developers
Classifier: Programming Language :: Python :: 3
Classifier: Operating System :: Microsoft :: Windows
Requires-Dist: absl-py (==1.4.0)
Requires-Dist: aiohttp (==3.8.3)
Requires-Dist: aiosignal (==1.3.1)
Requires-Dist: aiostream (==0.4.5)
Requires-Dist: astunparse (==1.6.3)
Requires-Dist: async-timeout (==4.0.2)
Requires-Dist: asyncio (==3.4.3)
Requires-Dist: attrs (==22.2.0)
Requires-Dist: bleach (==5.0.1)
Requires-Dist: boto (==2.49.0)
Requires-Dist: boto3 (==1.26.54)
Requires-Dist: botocore (==1.29.54)
Requires-Dist: bson (==0.5.10)
Requires-Dist: cached-property (==1.5.2)
Requires-Dist: cachetools (==5.2.1)
Requires-Dist: certifi (==2022.12.7)
Requires-Dist: cffi (==1.15.1)
Requires-Dist: charset-normalizer (==2.1.1)
Requires-Dist: contourpy (==1.0.7)
Requires-Dist: cryptography (==39.0.0)
Requires-Dist: cycler (==0.11.0)
Requires-Dist: defusedxml (==0.7.1)
Requires-Dist: dnspython (==2.3.0)
Requires-Dist: docutils (==0.19)
Requires-Dist: et-xmlfile (==1.1.0)
Requires-Dist: exchangelib (==4.9.0)
Requires-Dist: flatbuffers (==23.1.21)
Requires-Dist: fonttools (==4.38.0)
Requires-Dist: fpdf (==1.7.2)
Requires-Dist: frozenlist (==1.3.3)
Requires-Dist: gast (==0.4.0)
Requires-Dist: google-auth (==2.16.0)
Requires-Dist: google-auth-oauthlib (==0.4.6)
Requires-Dist: google-pasta (==0.2.0)
Requires-Dist: grpcio (==1.51.1)
Requires-Dist: h5py (==3.7.0)
Requires-Dist: idna (==3.4)
Requires-Dist: imgkit (==1.2.2)
Requires-Dist: importlib-metadata (==6.0.0)
Requires-Dist: importlib-resources (==5.10.2)
Requires-Dist: isodate (==0.6.1)
Requires-Dist: jaraco.classes (==3.2.3)
Requires-Dist: jmespath (==1.0.1)
Requires-Dist: joblib (==1.2.0)
Requires-Dist: kaleido (==0.2.1)
Requires-Dist: keras (==2.10.0)
Requires-Dist: Keras-Preprocessing (==1.1.2)
Requires-Dist: keyring (==23.13.1)
Requires-Dist: kiwisolver (==1.4.4)
Requires-Dist: libclang (==15.0.6.1)
Requires-Dist: lxml (==4.9.2)
Requires-Dist: Markdown (==3.4.1)
Requires-Dist: markdown-it-py (==2.1.0)
Requires-Dist: MarkupSafe (==2.1.2)
Requires-Dist: matplotlib (==3.6.3)
Requires-Dist: mdurl (==0.1.2)
Requires-Dist: more-itertools (==9.0.0)
Requires-Dist: msal (==1.20.0)
Requires-Dist: multidict (==6.0.4)
Requires-Dist: ndg-httpsclient (==0.5.1)
Requires-Dist: ntlm-auth (==1.5.0)
Requires-Dist: numpy (==1.24.1)
Requires-Dist: oauthlib (==3.2.2)
Requires-Dist: openpyxl (==3.0.10)
Requires-Dist: opt-einsum (==3.3.0)
Requires-Dist: packaging (==23.0)
Requires-Dist: pandas (==1.5.2)
Requires-Dist: pdfkit (==1.0.0)
Requires-Dist: pickle-mixin (==1.0.2)
Requires-Dist: Pillow (==9.4.0)
Requires-Dist: pkginfo (==1.9.6)
Requires-Dist: plotly (==5.12.0)
Requires-Dist: protobuf (==3.19.6)
Requires-Dist: psutil (==5.9.4)
Requires-Dist: pusher (==3.3.0)
Requires-Dist: pyasn1 (==0.4.8)
Requires-Dist: pyasn1-modules (==0.2.8)
Requires-Dist: pyclipper (==1.3.0.post4)
Requires-Dist: pycparser (==2.21)
Requires-Dist: Pygments (==2.14.0)
Requires-Dist: PyJWT (==2.6.0)
Requires-Dist: PyNaCl (==1.5.0)
Requires-Dist: pyOpenSSL (==23.0.0)
Requires-Dist: pyparsing (==3.0.9)
Requires-Dist: pyproj (==3.4.1)
Requires-Dist: python-dateutil (==2.8.2)
Requires-Dist: pytz (==2022.7.1)
Requires-Dist: pytz-deprecation-shim (==0.1.0.post0)
Requires-Dist: pywin32-ctypes (==0.2.0)
Requires-Dist: readme-renderer (==37.3)
Requires-Dist: requests (==2.28.2)
Requires-Dist: requests-ntlm (==1.1.0)
Requires-Dist: requests-oauthlib (==1.3.1)
Requires-Dist: requests-toolbelt (==0.10.1)
Requires-Dist: RestrictedPython (==6.0)
Requires-Dist: rfc3986 (==2.0.0)
Requires-Dist: rich (==13.2.0)
Requires-Dist: rsa (==4.9)
Requires-Dist: s3transfer (==0.6.0)
Requires-Dist: scikit-learn (==1.2.0)
Requires-Dist: scipy (==1.10.0)
Requires-Dist: shapely (==2.0.0)
Requires-Dist: six (==1.16.0)
Requires-Dist: sklearn (==0.0.post1)
Requires-Dist: staticmap (==0.5.5)
Requires-Dist: tenacity (==8.1.0)
Requires-Dist: tensorboard (==2.10.0)
Requires-Dist: tensorboard-data-server (==0.6.1)
Requires-Dist: tensorboard-plugin-wit (==1.8.1)
Requires-Dist: tensorflow (==2.10.0)
Requires-Dist: tensorflow-estimator (==2.10.0)
Requires-Dist: tensorflow-hub (==0.12.0)
Requires-Dist: tensorflow-io-gcs-filesystem (==0.30.0)
Requires-Dist: tensorflow-text (==2.10.0)
Requires-Dist: tensorflow-intel (==2.10.0)
Requires-Dist: termcolor (==2.2.0)
Requires-Dist: threadpoolctl (==3.1.0)
Requires-Dist: twine (==4.0.2)
Requires-Dist: typing-extensions (==4.4.0)
Requires-Dist: tzdata (==2022.7)
Requires-Dist: tzlocal (==4.2)
Requires-Dist: urllib3 (==1.26.14)
Requires-Dist: webencodings (==0.5.1)
Requires-Dist: Werkzeug (==2.2.2)
Requires-Dist: wrapt (==1.14.1)
Requires-Dist: xgboost (==1.7.3)
Requires-Dist: XlsxWriter (==3.0.7)
Requires-Dist: yarl (==1.8.2)
Requires-Dist: zipp (==3.11.0)
Requires-Dist: backports.zoneinfo (==0.2.1) ; python_version < "3.9"
